frunner/__init__.py
frunner/case.py
frunner/cli.py
frunner/scaffold.py
frunner/core/__init__.py
frunner/core/android/__init__.py
frunner/core/android/case.py
frunner/core/android/driver.py
frunner/core/android/element.py
frunner/core/api/__init__.py
frunner/core/api/case.py
frunner/core/api/request.py
frunner/core/h5/__init__.py
frunner/core/h5/driver.py
frunner/core/image/__init__.py
frunner/core/image/element.py
frunner/core/image/exceptions.py
frunner/core/image/matching/__init__.py
frunner/core/image/matching/keypoint/__init__.py
frunner/core/image/matching/keypoint/base.py
frunner/core/image/matching/keypoint/sift/__init__.py
frunner/core/image/matching/keypoint/sift/sift.py
frunner/core/image/matching/template/__init__.py
frunner/core/image/matching/template/matchTemplate.py
frunner/core/image/utils/__init__.py
frunner/core/ios/__init__.py
frunner/core/ios/case.py
frunner/core/ios/driver.py
frunner/core/ios/element.py
frunner/core/pc/__init__.py
frunner/core/pc/driver.py
frunner/core/remote/__init__.py
frunner/core/remote/remote.py
frunner/core/web/__init__.py
frunner/core/web/case.py
frunner/core/web/driver.py
frunner/core/web/element.py
frunner/running/__init__.py
frunner/running/conf.yml
frunner/running/runner.py
frunner/utils/__init__.py
frunner/utils/allure_data.py
frunner/utils/config.py
frunner/utils/data.py
frunner/utils/decorate.py
frunner/utils/dingtalk.py
frunner/utils/excel.py
frunner/utils/exceptions.py
frunner/utils/jira.py
frunner/utils/log.py
frunner/utils/mail.py
frunner/utils/mock.py
frunner/utils/mongo_util.py
frunner/utils/mysql_util.py
frunner/utils/swagger.py
frunner/utils/webdriver_manager_extend.py
frunner/utils/faker/__init__.py
frunner/utils/faker/__main__.py
frunner/utils/faker/cli.py
frunner/utils/faker/config.py
frunner/utils/faker/documentor.py
frunner/utils/faker/exceptions.py
frunner/utils/faker/factory.py
frunner/utils/faker/generator.py
frunner/utils/faker/proxy.py
frunner/utils/faker/py.typed
frunner/utils/faker/typing.py
frunner-1.0.5.dist-info/LICENSE
frunner-1.0.5.dist-info/METADATA
frunner-1.0.5.dist-info/WHEEL
frunner-1.0.5.dist-info/entry_points.txt
frunner-1.0.5.dist-info/top_level.txt
frunner-1.0.5.dist-info/RECORD
